README.md
setup.py
godefine/__init__.py
godefine/__main__.py
godefine/consts.py
godefine/core.py
godefine.egg-info/PKG-INFO
godefine.egg-info/SOURCES.txt
godefine.egg-info/dependency_links.txt
godefine.egg-info/entry_points.txt
godefine.egg-info/requires.txt
godefine.egg-info/top_level.txt