Metadata-Version: 2.1
Name: godefine
Version: 1.1.2
Summary: preprocess marcos tool
Home-page: https://github.com/ooopSnake/godefine
Author: suzhen
Author-email: suzhen@homeinpocket.net
License: MIT License
Platform: all
Classifier: Programming Language :: Python :: 3.0
Classifier: Topic :: Software Development :: Code Generators
Classifier: Operating System :: OS Independent
Requires-Python: >=3.4
